SP2000/__init__.py
SP2000/sp2000.py
SP2000-0.11.dist-info/LICENSE
SP2000-0.11.dist-info/METADATA
SP2000-0.11.dist-info/WHEEL
SP2000-0.11.dist-info/top_level.txt
SP2000-0.11.dist-info/RECORD
