Metadata-Version: 2.1
Name: SP2000
Version: 0.11
Summary: sp2000 python
Home-page: https://github.com/ynulihao/SP2000
Author: Hao Li
Author-email: lihao@mail.ynu.edu.cn
License: UNKNOWN
Platform: UNKNOWN
Classifier: Programming Language :: Python :: 3
Classifier: License :: OSI Approved :: MIT License
Classifier: Operating System :: OS Independent
Requires-Dist: pandas
Requires-Dist: requests
